yafowil.yaml-2.0-nspkg.pth
yafowil/yaml/__init__.py
yafowil/yaml/demo_form.yaml
yafowil/yaml/parser.py
yafowil/yaml/sphinx.rst
yafowil/yaml/tests.py
yafowil.yaml-2.0.dist-info/LICENSE.rst
yafowil.yaml-2.0.dist-info/METADATA
yafowil.yaml-2.0.dist-info/WHEEL
yafowil.yaml-2.0.dist-info/namespace_packages.txt
yafowil.yaml-2.0.dist-info/top_level.txt
yafowil.yaml-2.0.dist-info/RECORD
