Metadata-Version: 2.1
Name: yafowil.yaml
Version: 2.0
Summary: YAFOWIL - YAML/JSON-parser for widget trees.
Home-page: http://github.com/conestack/yafowil.yaml
Author: Yafowil Contributors
Author-email: dev@conestack.org
License: Simplified BSD
Keywords: html input widgets form compound
Platform: UNKNOWN
Classifier: Operating System :: OS Independent
Classifier: Programming Language :: Python
Classifier: Topic :: Software Development
Classifier: Topic :: Internet :: WWW/HTTP :: Dynamic Content
Classifier: License :: OSI Approved :: BSD License
Classifier: Programming Language :: Python :: 2.7
Classifier: Programming Language :: Python :: 3.5
Classifier: Programming Language :: Python :: 3.6
Classifier: Programming Language :: Python :: 3.7
Requires-Dist: PyYAML
Requires-Dist: setuptools
Requires-Dist: yafowil (>1.0.4)
Provides-Extra: test
Requires-Dist: yafowil[test] ; extra == 'test'
